enumatch/__init__.py
enumatch-0.2.0.dist-info/LICENSE
enumatch-0.2.0.dist-info/WHEEL
enumatch-0.2.0.dist-info/METADATA
enumatch-0.2.0.dist-info/RECORD
