Metadata-Version: 2.1
Name: enumatch
Version: 0.2.0
Summary: Strictly match all the possibilities of an enum
Home-page: https://github.com/sayanarijit/enumatch
License: MIT
Keywords: enum,match,functional
Author: Arijit Basu
Author-email: sayanarijit@gmail.com
Requires-Python: >=3.6,<4.0
Classifier: License :: OSI Approved :: MIT License
Classifier: Programming Language :: Python :: 3
Classifier: Programming Language :: Python :: 3.6
Classifier: Programming Language :: Python :: 3.7
Classifier: Programming Language :: Python :: 3.8
